ace_cm/__init__.py
ace_cm/cm.py
ace_cm/ecm.py
ace_cm/test.py
ace_cookie_manager-0.0.1.dist-info/LICENSES.txt
ace_cookie_manager-0.0.1.dist-info/METADATA
ace_cookie_manager-0.0.1.dist-info/WHEEL
ace_cookie_manager-0.0.1.dist-info/top_level.txt
ace_cookie_manager-0.0.1.dist-info/RECORD
